{
  "doc_id": "doc_9d120e40-0188-4f71-9906-c46fd92c2cf1",
  "doc_category": "obs_table",
  "template_id": "obs_date_body_measurements_v1",
  "patient_id": "pat_10339b10-3cd1-4ac3-ac13-ec26728cb592",
  "grouping_type": "date",
  "grouping": "2014-08-05",
  "entities_provided": {
    "observations": [
      {
        "entity_id": "obs_14177420-5acf-11f1-ad28-00155d199340",
        "fields": [
          "description",
          "encounter",
          "value",
          "units"
        ]
      },
      {
        "entity_id": "obs_14177588-5acf-11f1-ad28-00155d199340",
        "fields": [
          "description",
          "encounter",
          "value",
          "units"
        ]
      },
      {
        "entity_id": "obs_1417759c-5acf-11f1-ad28-00155d199340",
        "fields": [
          "description",
          "encounter",
          "value",
          "units"
        ]
      }
    ]
  }
}