{
  "_carePlans": "careplans are excluded because their information is largely redundant with medications + procedures",
  "_imaging_studies": "imaging studies are excluded as synthea data does not include descriptions",
  "patient": {
    "id": "pat_593548b9-2898-4fcc-b457-2ade24d11123",
    "firstName": "Tonja658",
    "lastName": "Jast432",
    "dob": "1949-09-04",
    "gender": "F",
    "entities": []
  },
  "allergies": [],
  "careplans": [
    {
      "id": "care_72953980-ab99-4820-84d9-64a39c60c4e7",
      "startDate": "1993-08-24",
      "endDate": NaN,
      "encounter": "5232cc4c-0cfc-44ab-901c-1f8e58af3974",
      "description": "Musculoskeletal care",
      "reasonDescription": "Osteoarthritis of knee"
    }
  ],
  "devices": [],
  "encounters": [
    {
      "id": "enc_dc4eccbb-da38-412f-beac-8e624f6e8e34",
      "type": "wellness",
      "description": "General examination of patient (procedure)",
      "reason": NaN,
      "startDate": "1989-09-10",
      "endDate": "1989-09-10",
      "startTime": "20:51:57",
      "endTime": "21:06:57"
    },
    {
      "id": "enc_5232cc4c-0cfc-44ab-901c-1f8e58af3974",
      "type": "ambulatory",
      "description": "Encounter for problem",
      "reason": "Osteoarthritis of knee",
      "startDate": "1993-08-24",
      "endDate": "1993-08-24",
      "startTime": "20:51:57",
      "endTime": "21:06:57"
    },
    {
      "id": "enc_b58e1761-52b5-4874-b54a-2efb60fff2bc",
      "type": "wellness",
      "description": "General examination of patient (procedure)",
      "reason": NaN,
      "startDate": "2009-11-01",
      "endDate": "2009-11-01",
      "startTime": "20:51:57",
      "endTime": "21:21:57"
    },
    {
      "id": "enc_b421d9e4-1c24-4ce7-b17f-03a88a943096",
      "type": "wellness",
      "description": "General examination of patient (procedure)",
      "reason": NaN,
      "startDate": "2010-11-07",
      "endDate": "2010-11-07",
      "startTime": "20:51:57",
      "endTime": "21:21:57"
    },
    {
      "id": "enc_da1a5b04-0bfc-4664-bc95-79aa5b713a7c",
      "type": "wellness",
      "description": "General examination of patient (procedure)",
      "reason": NaN,
      "startDate": "2011-11-13",
      "endDate": "2011-11-13",
      "startTime": "20:51:57",
      "endTime": "21:06:57"
    },
    {
      "id": "enc_aedbc72f-0a71-404f-87d5-fcfd5dfa0b08",
      "type": "wellness",
      "description": "General examination of patient (procedure)",
      "reason": NaN,
      "startDate": "2012-11-18",
      "endDate": "2012-11-18",
      "startTime": "20:51:57",
      "endTime": "21:21:57"
    },
    {
      "id": "enc_4fe67c42-a82c-4991-bd2c-5507eef12c1d",
      "type": "wellness",
      "description": "General examination of patient (procedure)",
      "reason": NaN,
      "startDate": "2013-11-24",
      "endDate": "2013-11-24",
      "startTime": "20:51:57",
      "endTime": "21:21:57"
    },
    {
      "id": "enc_412dc8ae-865d-4967-aea4-eba5e868eade",
      "type": "ambulatory",
      "description": "Encounter for 'check-up'",
      "reason": NaN,
      "startDate": "2014-09-01",
      "endDate": "2014-09-01",
      "startTime": "20:51:57",
      "endTime": "21:42:57"
    },
    {
      "id": "enc_a096fa67-5b05-4d73-8041-d1263a961df9",
      "type": "wellness",
      "description": "General examination of patient (procedure)",
      "reason": NaN,
      "startDate": "2014-11-30",
      "endDate": "2014-11-30",
      "startTime": "20:51:57",
      "endTime": "21:06:57"
    },
    {
      "id": "enc_e221c708-c1e0-47de-9c7a-b949a69ff842",
      "type": "wellness",
      "description": "General examination of patient (procedure)",
      "reason": NaN,
      "startDate": "2015-12-06",
      "endDate": "2015-12-06",
      "startTime": "20:51:57",
      "endTime": "21:06:57"
    },
    {
      "id": "enc_d710d8ac-aa5e-43a8-a12c-dc4299764be5",
      "type": "wellness",
      "description": "General examination of patient (procedure)",
      "reason": NaN,
      "startDate": "2016-12-11",
      "endDate": "2016-12-11",
      "startTime": "20:51:57",
      "endTime": "21:06:57"
    },
    {
      "id": "enc_67fecb71-e430-4454-965d-ef1b7e70b248",
      "type": "wellness",
      "description": "General examination of patient (procedure)",
      "reason": NaN,
      "startDate": "2017-12-17",
      "endDate": "2017-12-17",
      "startTime": "20:51:57",
      "endTime": "21:06:57"
    },
    {
      "id": "enc_5d1d35d0-2432-434b-8613-11e3ff6d968a",
      "type": "wellness",
      "description": "General examination of patient (procedure)",
      "reason": NaN,
      "startDate": "2018-12-23",
      "endDate": "2018-12-23",
      "startTime": "20:51:57",
      "endTime": "21:06:57"
    },
    {
      "id": "enc_146322e5-c725-424a-85fe-705549ad4829",
      "type": "ambulatory",
      "description": "Encounter for 'check-up'",
      "reason": NaN,
      "startDate": "2019-08-31",
      "endDate": "2019-08-31",
      "startTime": "20:51:57",
      "endTime": "21:49:57"
    },
    {
      "id": "enc_a6605445-1c2b-4dcb-bccf-67d214e9ba6e",
      "type": "wellness",
      "description": "General examination of patient (procedure)",
      "reason": NaN,
      "startDate": "2019-12-29",
      "endDate": "2019-12-29",
      "startTime": "20:51:57",
      "endTime": "21:21:57"
    }
  ],
  "imaging_studies": [],
  "conditions": [
    {
      "condition": "Body mass index 30+ - obesity (finding)",
      "id": "cond_718c96aa-5a32-11f1-afc7-00155dba74fb",
      "encounter": "dc4eccbb-da38-412f-beac-8e624f6e8e34",
      "startDate": "1989-09-10",
      "endDate": null
    },
    {
      "condition": "Osteoarthritis of knee",
      "id": "cond_718c97d6-5a32-11f1-afc7-00155dba74fb",
      "encounter": "5232cc4c-0cfc-44ab-901c-1f8e58af3974",
      "startDate": "1993-08-24",
      "endDate": null
    },
    {
      "condition": "Osteoporosis (disorder)",
      "id": "cond_718c98f8-5a32-11f1-afc7-00155dba74fb",
      "encounter": "b58e1761-52b5-4874-b54a-2efb60fff2bc",
      "startDate": "2009-11-01",
      "endDate": null
    }
  ],
  "immunizations": [
    {
      "name": "Influenza  seasonal  injectable  preservative free",
      "id": "immu_71a3693e-5a32-11f1-afc7-00155dba74fb",
      "date": "2010-11-07",
      "encounter": "b421d9e4-1c24-4ce7-b17f-03a88a943096"
    },
    {
      "name": "Td (adult) preservative free",
      "id": "immu_71a36952-5a32-11f1-afc7-00155dba74fb",
      "date": "2010-11-07",
      "encounter": "b421d9e4-1c24-4ce7-b17f-03a88a943096"
    },
    {
      "name": "Influenza  seasonal  injectable  preservative free",
      "id": "immu_71a3695c-5a32-11f1-afc7-00155dba74fb",
      "date": "2011-11-13",
      "encounter": "da1a5b04-0bfc-4664-bc95-79aa5b713a7c"
    },
    {
      "name": "Influenza  seasonal  injectable  preservative free",
      "id": "immu_71a36970-5a32-11f1-afc7-00155dba74fb",
      "date": "2012-11-18",
      "encounter": "aedbc72f-0a71-404f-87d5-fcfd5dfa0b08"
    },
    {
      "name": "Influenza  seasonal  injectable  preservative free",
      "id": "immu_71a3697a-5a32-11f1-afc7-00155dba74fb",
      "date": "2013-11-24",
      "encounter": "4fe67c42-a82c-4991-bd2c-5507eef12c1d"
    },
    {
      "name": "Influenza  seasonal  injectable  preservative free",
      "id": "immu_71a3698e-5a32-11f1-afc7-00155dba74fb",
      "date": "2014-11-30",
      "encounter": "a096fa67-5b05-4d73-8041-d1263a961df9"
    },
    {
      "name": "Pneumococcal conjugate PCV 13",
      "id": "immu_71a36998-5a32-11f1-afc7-00155dba74fb",
      "date": "2014-11-30",
      "encounter": "a096fa67-5b05-4d73-8041-d1263a961df9"
    },
    {
      "name": "Influenza  seasonal  injectable  preservative free",
      "id": "immu_71a369ac-5a32-11f1-afc7-00155dba74fb",
      "date": "2015-12-06",
      "encounter": "e221c708-c1e0-47de-9c7a-b949a69ff842"
    },
    {
      "name": "pneumococcal polysaccharide vaccine  23 valent",
      "id": "immu_71a369b6-5a32-11f1-afc7-00155dba74fb",
      "date": "2015-12-06",
      "encounter": "e221c708-c1e0-47de-9c7a-b949a69ff842"
    },
    {
      "name": "Influenza  seasonal  injectable  preservative free",
      "id": "immu_71a369ca-5a32-11f1-afc7-00155dba74fb",
      "date": "2016-12-11",
      "encounter": "d710d8ac-aa5e-43a8-a12c-dc4299764be5"
    },
    {
      "name": "Influenza  seasonal  injectable  preservative free",
      "id": "immu_71a369d4-5a32-11f1-afc7-00155dba74fb",
      "date": "2017-12-17",
      "encounter": "67fecb71-e430-4454-965d-ef1b7e70b248"
    },
    {
      "name": "Influenza  seasonal  injectable  preservative free",
      "id": "immu_71a369e8-5a32-11f1-afc7-00155dba74fb",
      "date": "2018-12-23",
      "encounter": "5d1d35d0-2432-434b-8613-11e3ff6d968a"
    },
    {
      "name": "Influenza  seasonal  injectable  preservative free",
      "id": "immu_71a369f2-5a32-11f1-afc7-00155dba74fb",
      "date": "2019-12-29",
      "encounter": "a6605445-1c2b-4dcb-bccf-67d214e9ba6e"
    }
  ],
  "medications": [
    {
      "description": "Naproxen sodium 220 MG Oral Tablet",
      "id": "med_71b7d61c-5a32-11f1-afc7-00155dba74fb",
      "encounter": "5232cc4c-0cfc-44ab-901c-1f8e58af3974",
      "reason": "Osteoarthritis of knee",
      "startDate": "1993-08-24",
      "endDate": null
    },
    {
      "description": "Alendronic acid 10 MG Oral Tablet",
      "id": "med_71b7d63a-5a32-11f1-afc7-00155dba74fb",
      "encounter": "b58e1761-52b5-4874-b54a-2efb60fff2bc",
      "reason": NaN,
      "startDate": "2009-11-01",
      "endDate": null
    }
  ],
  "procedures": [
    {
      "description": "Medication Reconciliation (procedure)",
      "id": "proc_71c9a694-5a32-11f1-afc7-00155dba74fb",
      "encounter": "b421d9e4-1c24-4ce7-b17f-03a88a943096",
      "reason": NaN,
      "date": "2010-11-07",
      "time": "20:51:57Z"
    },
    {
      "description": "Medication Reconciliation (procedure)",
      "id": "proc_71c9a6a8-5a32-11f1-afc7-00155dba74fb",
      "encounter": "aedbc72f-0a71-404f-87d5-fcfd5dfa0b08",
      "reason": NaN,
      "date": "2012-11-18",
      "time": "20:51:57Z"
    },
    {
      "description": "Medication Reconciliation (procedure)",
      "id": "proc_71c9a6b2-5a32-11f1-afc7-00155dba74fb",
      "encounter": "4fe67c42-a82c-4991-bd2c-5507eef12c1d",
      "reason": NaN,
      "date": "2013-11-24",
      "time": "20:51:57Z"
    },
    {
      "description": "Colonoscopy",
      "id": "proc_71c9a6c6-5a32-11f1-afc7-00155dba74fb",
      "encounter": "412dc8ae-865d-4967-aea4-eba5e868eade",
      "reason": NaN,
      "date": "2014-09-01",
      "time": "20:51:57Z"
    },
    {
      "description": "Colonoscopy",
      "id": "proc_71c9a6d0-5a32-11f1-afc7-00155dba74fb",
      "encounter": "146322e5-c725-424a-85fe-705549ad4829",
      "reason": NaN,
      "date": "2019-08-31",
      "time": "20:51:57Z"
    },
    {
      "description": "Medication Reconciliation (procedure)",
      "id": "proc_71c9a702-5a32-11f1-afc7-00155dba74fb",
      "encounter": "a6605445-1c2b-4dcb-bccf-67d214e9ba6e",
      "reason": NaN,
      "date": "2019-12-29",
      "time": "20:51:57Z"
    }
  ],
  "observations": [
    {
      "description": "Body Height",
      "id": "obs_7210b6ec-5a32-11f1-afc7-00155dba74fb",
      "encounter": "b421d9e4-1c24-4ce7-b17f-03a88a943096",
      "value": "171.6",
      "units": "cm",
      "date": "2010-11-07",
      "category": "body_measurement"
    },
    {
      "description": "Pain severity - 0-10 verbal numeric rating [Score] - Reported",
      "id": "obs_7210b700-5a32-11f1-afc7-00155dba74fb",
      "encounter": "b421d9e4-1c24-4ce7-b17f-03a88a943096",
      "value": "1.0",
      "units": "{score}",
      "date": "2010-11-07",
      "category": "other"
    },
    {
      "description": "Body Weight",
      "id": "obs_7210b714-5a32-11f1-afc7-00155dba74fb",
      "encounter": "b421d9e4-1c24-4ce7-b17f-03a88a943096",
      "value": "82.7",
      "units": "kg",
      "date": "2010-11-07",
      "category": "body_measurement"
    },
    {
      "description": "Body Mass Index",
      "id": "obs_7210b728-5a32-11f1-afc7-00155dba74fb",
      "encounter": "b421d9e4-1c24-4ce7-b17f-03a88a943096",
      "value": "28.1",
      "units": "kg/m2",
      "date": "2010-11-07",
      "category": "body_measurement"
    },
    {
      "description": "Diastolic Blood Pressure",
      "id": "obs_7210b732-5a32-11f1-afc7-00155dba74fb",
      "encounter": "b421d9e4-1c24-4ce7-b17f-03a88a943096",
      "value": "79.0",
      "units": "mm[Hg]",
      "date": "2010-11-07",
      "category": "other"
    },
    {
      "description": "Systolic Blood Pressure",
      "id": "obs_7210b746-5a32-11f1-afc7-00155dba74fb",
      "encounter": "b421d9e4-1c24-4ce7-b17f-03a88a943096",
      "value": "102.0",
      "units": "mm[Hg]",
      "date": "2010-11-07",
      "category": "other"
    },
    {
      "description": "Heart rate",
      "id": "obs_7210b75a-5a32-11f1-afc7-00155dba74fb",
      "encounter": "b421d9e4-1c24-4ce7-b17f-03a88a943096",
      "value": "94.0",
      "units": "/min",
      "date": "2010-11-07",
      "category": "other"
    },
    {
      "description": "Respiratory rate",
      "id": "obs_7210b764-5a32-11f1-afc7-00155dba74fb",
      "encounter": "b421d9e4-1c24-4ce7-b17f-03a88a943096",
      "value": "14.0",
      "units": "/min",
      "date": "2010-11-07",
      "category": "other"
    },
    {
      "description": "Tobacco smoking status NHIS",
      "id": "obs_7210b778-5a32-11f1-afc7-00155dba74fb",
      "encounter": "b421d9e4-1c24-4ce7-b17f-03a88a943096",
      "value": "Former smoker",
      "units": NaN,
      "date": "2010-11-07",
      "category": "other"
    },
    {
      "description": "Body Height",
      "id": "obs_7210b78c-5a32-11f1-afc7-00155dba74fb",
      "encounter": "da1a5b04-0bfc-4664-bc95-79aa5b713a7c",
      "value": "171.6",
      "units": "cm",
      "date": "2011-11-13",
      "category": "body_measurement"
    },
    {
      "description": "Pain severity - 0-10 verbal numeric rating [Score] - Reported",
      "id": "obs_7210b7a0-5a32-11f1-afc7-00155dba74fb",
      "encounter": "da1a5b04-0bfc-4664-bc95-79aa5b713a7c",
      "value": "0.0",
      "units": "{score}",
      "date": "2011-11-13",
      "category": "other"
    },
    {
      "description": "Body Weight",
      "id": "obs_7210b7b4-5a32-11f1-afc7-00155dba74fb",
      "encounter": "da1a5b04-0bfc-4664-bc95-79aa5b713a7c",
      "value": "84.9",
      "units": "kg",
      "date": "2011-11-13",
      "category": "body_measurement"
    },
    {
      "description": "Body Mass Index",
      "id": "obs_7210b7c8-5a32-11f1-afc7-00155dba74fb",
      "encounter": "da1a5b04-0bfc-4664-bc95-79aa5b713a7c",
      "value": "28.8",
      "units": "kg/m2",
      "date": "2011-11-13",
      "category": "body_measurement"
    },
    {
      "description": "Diastolic Blood Pressure",
      "id": "obs_7210b7dc-5a32-11f1-afc7-00155dba74fb",
      "encounter": "da1a5b04-0bfc-4664-bc95-79aa5b713a7c",
      "value": "79.0",
      "units": "mm[Hg]",
      "date": "2011-11-13",
      "category": "other"
    },
    {
      "description": "Systolic Blood Pressure",
      "id": "obs_7210b7fa-5a32-11f1-afc7-00155dba74fb",
      "encounter": "da1a5b04-0bfc-4664-bc95-79aa5b713a7c",
      "value": "118.0",
      "units": "mm[Hg]",
      "date": "2011-11-13",
      "category": "other"
    },
    {
      "description": "Heart rate",
      "id": "obs_7210b804-5a32-11f1-afc7-00155dba74fb",
      "encounter": "da1a5b04-0bfc-4664-bc95-79aa5b713a7c",
      "value": "89.0",
      "units": "/min",
      "date": "2011-11-13",
      "category": "other"
    },
    {
      "description": "Respiratory rate",
      "id": "obs_7210b818-5a32-11f1-afc7-00155dba74fb",
      "encounter": "da1a5b04-0bfc-4664-bc95-79aa5b713a7c",
      "value": "15.0",
      "units": "/min",
      "date": "2011-11-13",
      "category": "other"
    },
    {
      "description": "Total Cholesterol",
      "id": "obs_7210b82c-5a32-11f1-afc7-00155dba74fb",
      "encounter": "da1a5b04-0bfc-4664-bc95-79aa5b713a7c",
      "value": "166.3",
      "units": "mg/dL",
      "date": "2011-11-13",
      "category": "other"
    },
    {
      "description": "Triglycerides",
      "id": "obs_7210b836-5a32-11f1-afc7-00155dba74fb",
      "encounter": "da1a5b04-0bfc-4664-bc95-79aa5b713a7c",
      "value": "114.9",
      "units": "mg/dL",
      "date": "2011-11-13",
      "category": "other"
    },
    {
      "description": "Low Density Lipoprotein Cholesterol",
      "id": "obs_7210b84a-5a32-11f1-afc7-00155dba74fb",
      "encounter": "da1a5b04-0bfc-4664-bc95-79aa5b713a7c",
      "value": "64.6",
      "units": "mg/dL",
      "date": "2011-11-13",
      "category": "other"
    },
    {
      "description": "High Density Lipoprotein Cholesterol",
      "id": "obs_7210b85e-5a32-11f1-afc7-00155dba74fb",
      "encounter": "da1a5b04-0bfc-4664-bc95-79aa5b713a7c",
      "value": "78.6",
      "units": "mg/dL",
      "date": "2011-11-13",
      "category": "other"
    },
    {
      "description": "Leukocytes [#/volume] in Blood by Automated count",
      "id": "obs_7210b868-5a32-11f1-afc7-00155dba74fb",
      "encounter": "da1a5b04-0bfc-4664-bc95-79aa5b713a7c",
      "value": "9.2",
      "units": "10*3/uL",
      "date": "2011-11-13",
      "category": "other"
    },
    {
      "description": "Erythrocytes [#/volume] in Blood by Automated count",
      "id": "obs_7210b87c-5a32-11f1-afc7-00155dba74fb",
      "encounter": "da1a5b04-0bfc-4664-bc95-79aa5b713a7c",
      "value": "5.4",
      "units": "10*6/uL",
      "date": "2011-11-13",
      "category": "other"
    },
    {
      "description": "Hemoglobin [Mass/volume] in Blood",
      "id": "obs_7210b890-5a32-11f1-afc7-00155dba74fb",
      "encounter": "da1a5b04-0bfc-4664-bc95-79aa5b713a7c",
      "value": "13.2",
      "units": "g/dL",
      "date": "2011-11-13",
      "category": "other"
    },
    {
      "description": "Hematocrit [Volume Fraction] of Blood by Automated count",
      "id": "obs_7210b89a-5a32-11f1-afc7-00155dba74fb",
      "encounter": "da1a5b04-0bfc-4664-bc95-79aa5b713a7c",
      "value": "37.1",
      "units": "%",
      "date": "2011-11-13",
      "category": "other"
    },
    {
      "description": "MCV [Entitic volume] by Automated count",
      "id": "obs_7210b8ae-5a32-11f1-afc7-00155dba74fb",
      "encounter": "da1a5b04-0bfc-4664-bc95-79aa5b713a7c",
      "value": "89.1",
      "units": "fL",
      "date": "2011-11-13",
      "category": "other"
    },
    {
      "description": "MCH [Entitic mass] by Automated count",
      "id": "obs_7210b8c2-5a32-11f1-afc7-00155dba74fb",
      "encounter": "da1a5b04-0bfc-4664-bc95-79aa5b713a7c",
      "value": "31.1",
      "units": "pg",
      "date": "2011-11-13",
      "category": "other"
    },
    {
      "description": "MCHC [Mass/volume] by Automated count",
      "id": "obs_7210b8cc-5a32-11f1-afc7-00155dba74fb",
      "encounter": "da1a5b04-0bfc-4664-bc95-79aa5b713a7c",
      "value": "33.9",
      "units": "g/dL",
      "date": "2011-11-13",
      "category": "other"
    },
    {
      "description": "Erythrocyte distribution width [Entitic volume] by Automated count",
      "id": "obs_7210b8e0-5a32-11f1-afc7-00155dba74fb",
      "encounter": "da1a5b04-0bfc-4664-bc95-79aa5b713a7c",
      "value": "42.1",
      "units": "fL",
      "date": "2011-11-13",
      "category": "other"
    },
    {
      "description": "Platelets [#/volume] in Blood by Automated count",
      "id": "obs_7210b8f4-5a32-11f1-afc7-00155dba74fb",
      "encounter": "da1a5b04-0bfc-4664-bc95-79aa5b713a7c",
      "value": "253.9",
      "units": "10*3/uL",
      "date": "2011-11-13",
      "category": "other"
    },
    {
      "description": "Platelet distribution width [Entitic volume] in Blood by Automated count",
      "id": "obs_7210b8fe-5a32-11f1-afc7-00155dba74fb",
      "encounter": "da1a5b04-0bfc-4664-bc95-79aa5b713a7c",
      "value": "455.5",
      "units": "fL",
      "date": "2011-11-13",
      "category": "other"
    },
    {
      "description": "Platelet mean volume [Entitic volume] in Blood by Automated count",
      "id": "obs_7210b912-5a32-11f1-afc7-00155dba74fb",
      "encounter": "da1a5b04-0bfc-4664-bc95-79aa5b713a7c",
      "value": "9.7",
      "units": "fL",
      "date": "2011-11-13",
      "category": "other"
    },
    {
      "description": "Tobacco smoking status NHIS",
      "id": "obs_7210b930-5a32-11f1-afc7-00155dba74fb",
      "encounter": "da1a5b04-0bfc-4664-bc95-79aa5b713a7c",
      "value": "Former smoker",
      "units": NaN,
      "date": "2011-11-13",
      "category": "other"
    },
    {
      "description": "Body Height",
      "id": "obs_7210ba48-5a32-11f1-afc7-00155dba74fb",
      "encounter": "aedbc72f-0a71-404f-87d5-fcfd5dfa0b08",
      "value": "171.6",
      "units": "cm",
      "date": "2012-11-18",
      "category": "body_measurement"
    },
    {
      "description": "Pain severity - 0-10 verbal numeric rating [Score] - Reported",
      "id": "obs_7210baac-5a32-11f1-afc7-00155dba74fb",
      "encounter": "aedbc72f-0a71-404f-87d5-fcfd5dfa0b08",
      "value": "4.0",
      "units": "{score}",
      "date": "2012-11-18",
      "category": "other"
    },
    {
      "description": "Body Weight",
      "id": "obs_7210baca-5a32-11f1-afc7-00155dba74fb",
      "encounter": "aedbc72f-0a71-404f-87d5-fcfd5dfa0b08",
      "value": "87.1",
      "units": "kg",
      "date": "2012-11-18",
      "category": "body_measurement"
    },
    {
      "description": "Body Mass Index",
      "id": "obs_7210bade-5a32-11f1-afc7-00155dba74fb",
      "encounter": "aedbc72f-0a71-404f-87d5-fcfd5dfa0b08",
      "value": "29.6",
      "units": "kg/m2",
      "date": "2012-11-18",
      "category": "body_measurement"
    },
    {
      "description": "Diastolic Blood Pressure",
      "id": "obs_7210bafc-5a32-11f1-afc7-00155dba74fb",
      "encounter": "aedbc72f-0a71-404f-87d5-fcfd5dfa0b08",
      "value": "86.0",
      "units": "mm[Hg]",
      "date": "2012-11-18",
      "category": "other"
    },
    {
      "description": "Systolic Blood Pressure",
      "id": "obs_7210bb10-5a32-11f1-afc7-00155dba74fb",
      "encounter": "aedbc72f-0a71-404f-87d5-fcfd5dfa0b08",
      "value": "129.0",
      "units": "mm[Hg]",
      "date": "2012-11-18",
      "category": "other"
    },
    {
      "description": "Heart rate",
      "id": "obs_7210bb1a-5a32-11f1-afc7-00155dba74fb",
      "encounter": "aedbc72f-0a71-404f-87d5-fcfd5dfa0b08",
      "value": "92.0",
      "units": "/min",
      "date": "2012-11-18",
      "category": "other"
    },
    {
      "description": "Respiratory rate",
      "id": "obs_7210bb2e-5a32-11f1-afc7-00155dba74fb",
      "encounter": "aedbc72f-0a71-404f-87d5-fcfd5dfa0b08",
      "value": "14.0",
      "units": "/min",
      "date": "2012-11-18",
      "category": "other"
    },
    {
      "description": "Tobacco smoking status NHIS",
      "id": "obs_7210bb42-5a32-11f1-afc7-00155dba74fb",
      "encounter": "aedbc72f-0a71-404f-87d5-fcfd5dfa0b08",
      "value": "Former smoker",
      "units": NaN,
      "date": "2012-11-18",
      "category": "other"
    },
    {
      "description": "Body Height",
      "id": "obs_7210bb4c-5a32-11f1-afc7-00155dba74fb",
      "encounter": "4fe67c42-a82c-4991-bd2c-5507eef12c1d",
      "value": "171.6",
      "units": "cm",
      "date": "2013-11-24",
      "category": "body_measurement"
    },
    {
      "description": "Pain severity - 0-10 verbal numeric rating [Score] - Reported",
      "id": "obs_7210bb74-5a32-11f1-afc7-00155dba74fb",
      "encounter": "4fe67c42-a82c-4991-bd2c-5507eef12c1d",
      "value": "3.0",
      "units": "{score}",
      "date": "2013-11-24",
      "category": "other"
    },
    {
      "description": "Body Weight",
      "id": "obs_7210bb88-5a32-11f1-afc7-00155dba74fb",
      "encounter": "4fe67c42-a82c-4991-bd2c-5507eef12c1d",
      "value": "88.8",
      "units": "kg",
      "date": "2013-11-24",
      "category": "body_measurement"
    },
    {
      "description": "Body Mass Index",
      "id": "obs_7210bb9c-5a32-11f1-afc7-00155dba74fb",
      "encounter": "4fe67c42-a82c-4991-bd2c-5507eef12c1d",
      "value": "30.2",
      "units": "kg/m2",
      "date": "2013-11-24",
      "category": "body_measurement"
    },
    {
      "description": "Diastolic Blood Pressure",
      "id": "obs_7210bbb0-5a32-11f1-afc7-00155dba74fb",
      "encounter": "4fe67c42-a82c-4991-bd2c-5507eef12c1d",
      "value": "78.0",
      "units": "mm[Hg]",
      "date": "2013-11-24",
      "category": "other"
    },
    {
      "description": "Systolic Blood Pressure",
      "id": "obs_7210bbba-5a32-11f1-afc7-00155dba74fb",
      "encounter": "4fe67c42-a82c-4991-bd2c-5507eef12c1d",
      "value": "123.0",
      "units": "mm[Hg]",
      "date": "2013-11-24",
      "category": "other"
    },
    {
      "description": "Heart rate",
      "id": "obs_7210bbce-5a32-11f1-afc7-00155dba74fb",
      "encounter": "4fe67c42-a82c-4991-bd2c-5507eef12c1d",
      "value": "68.0",
      "units": "/min",
      "date": "2013-11-24",
      "category": "other"
    },
    {
      "description": "Respiratory rate",
      "id": "obs_7210bbe2-5a32-11f1-afc7-00155dba74fb",
      "encounter": "4fe67c42-a82c-4991-bd2c-5507eef12c1d",
      "value": "13.0",
      "units": "/min",
      "date": "2013-11-24",
      "category": "other"
    },
    {
      "description": "Tobacco smoking status NHIS",
      "id": "obs_7210bbf6-5a32-11f1-afc7-00155dba74fb",
      "encounter": "4fe67c42-a82c-4991-bd2c-5507eef12c1d",
      "value": "Former smoker",
      "units": NaN,
      "date": "2013-11-24",
      "category": "other"
    },
    {
      "description": "Body Height",
      "id": "obs_7210bc00-5a32-11f1-afc7-00155dba74fb",
      "encounter": "a096fa67-5b05-4d73-8041-d1263a961df9",
      "value": "171.6",
      "units": "cm",
      "date": "2014-11-30",
      "category": "body_measurement"
    },
    {
      "description": "Pain severity - 0-10 verbal numeric rating [Score] - Reported",
      "id": "obs_7210bc14-5a32-11f1-afc7-00155dba74fb",
      "encounter": "a096fa67-5b05-4d73-8041-d1263a961df9",
      "value": "4.0",
      "units": "{score}",
      "date": "2014-11-30",
      "category": "other"
    },
    {
      "description": "Body Weight",
      "id": "obs_7210bc28-5a32-11f1-afc7-00155dba74fb",
      "encounter": "a096fa67-5b05-4d73-8041-d1263a961df9",
      "value": "81.9",
      "units": "kg",
      "date": "2014-11-30",
      "category": "body_measurement"
    },
    {
      "description": "Body Mass Index",
      "id": "obs_7210bc3c-5a32-11f1-afc7-00155dba74fb",
      "encounter": "a096fa67-5b05-4d73-8041-d1263a961df9",
      "value": "27.8",
      "units": "kg/m2",
      "date": "2014-11-30",
      "category": "body_measurement"
    },
    {
      "description": "Diastolic Blood Pressure",
      "id": "obs_7210bc50-5a32-11f1-afc7-00155dba74fb",
      "encounter": "a096fa67-5b05-4d73-8041-d1263a961df9",
      "value": "81.0",
      "units": "mm[Hg]",
      "date": "2014-11-30",
      "category": "other"
    },
    {
      "description": "Systolic Blood Pressure",
      "id": "obs_7210bc64-5a32-11f1-afc7-00155dba74fb",
      "encounter": "a096fa67-5b05-4d73-8041-d1263a961df9",
      "value": "105.0",
      "units": "mm[Hg]",
      "date": "2014-11-30",
      "category": "other"
    },
    {
      "description": "Heart rate",
      "id": "obs_7210bc6e-5a32-11f1-afc7-00155dba74fb",
      "encounter": "a096fa67-5b05-4d73-8041-d1263a961df9",
      "value": "62.0",
      "units": "/min",
      "date": "2014-11-30",
      "category": "other"
    },
    {
      "description": "Respiratory rate",
      "id": "obs_7210bc82-5a32-11f1-afc7-00155dba74fb",
      "encounter": "a096fa67-5b05-4d73-8041-d1263a961df9",
      "value": "16.0",
      "units": "/min",
      "date": "2014-11-30",
      "category": "other"
    },
    {
      "description": "Total Cholesterol",
      "id": "obs_7210bc96-5a32-11f1-afc7-00155dba74fb",
      "encounter": "a096fa67-5b05-4d73-8041-d1263a961df9",
      "value": "193.8",
      "units": "mg/dL",
      "date": "2014-11-30",
      "category": "other"
    },
    {
      "description": "Triglycerides",
      "id": "obs_7210bca0-5a32-11f1-afc7-00155dba74fb",
      "encounter": "a096fa67-5b05-4d73-8041-d1263a961df9",
      "value": "115.4",
      "units": "mg/dL",
      "date": "2014-11-30",
      "category": "other"
    },
    {
      "description": "Low Density Lipoprotein Cholesterol",
      "id": "obs_7210bcb4-5a32-11f1-afc7-00155dba74fb",
      "encounter": "a096fa67-5b05-4d73-8041-d1263a961df9",
      "value": "107.0",
      "units": "mg/dL",
      "date": "2014-11-30",
      "category": "other"
    },
    {
      "description": "High Density Lipoprotein Cholesterol",
      "id": "obs_7210bcc8-5a32-11f1-afc7-00155dba74fb",
      "encounter": "a096fa67-5b05-4d73-8041-d1263a961df9",
      "value": "63.7",
      "units": "mg/dL",
      "date": "2014-11-30",
      "category": "other"
    },
    {
      "description": "Tobacco smoking status NHIS",
      "id": "obs_7210bcd2-5a32-11f1-afc7-00155dba74fb",
      "encounter": "a096fa67-5b05-4d73-8041-d1263a961df9",
      "value": "Former smoker",
      "units": NaN,
      "date": "2014-11-30",
      "category": "other"
    },
    {
      "description": "Body Height",
      "id": "obs_7210bce6-5a32-11f1-afc7-00155dba74fb",
      "encounter": "e221c708-c1e0-47de-9c7a-b949a69ff842",
      "value": "171.6",
      "units": "cm",
      "date": "2015-12-06",
      "category": "body_measurement"
    },
    {
      "description": "Pain severity - 0-10 verbal numeric rating [Score] - Reported",
      "id": "obs_7210bcfa-5a32-11f1-afc7-00155dba74fb",
      "encounter": "e221c708-c1e0-47de-9c7a-b949a69ff842",
      "value": "3.0",
      "units": "{score}",
      "date": "2015-12-06",
      "category": "other"
    },
    {
      "description": "Body Weight",
      "id": "obs_7210bd0e-5a32-11f1-afc7-00155dba74fb",
      "encounter": "e221c708-c1e0-47de-9c7a-b949a69ff842",
      "value": "83.8",
      "units": "kg",
      "date": "2015-12-06",
      "category": "body_measurement"
    },
    {
      "description": "Body Mass Index",
      "id": "obs_7210bd22-5a32-11f1-afc7-00155dba74fb",
      "encounter": "e221c708-c1e0-47de-9c7a-b949a69ff842",
      "value": "28.5",
      "units": "kg/m2",
      "date": "2015-12-06",
      "category": "body_measurement"
    },
    {
      "description": "Diastolic Blood Pressure",
      "id": "obs_7210bd2c-5a32-11f1-afc7-00155dba74fb",
      "encounter": "e221c708-c1e0-47de-9c7a-b949a69ff842",
      "value": "79.0",
      "units": "mm[Hg]",
      "date": "2015-12-06",
      "category": "other"
    },
    {
      "description": "Systolic Blood Pressure",
      "id": "obs_7210bd40-5a32-11f1-afc7-00155dba74fb",
      "encounter": "e221c708-c1e0-47de-9c7a-b949a69ff842",
      "value": "122.0",
      "units": "mm[Hg]",
      "date": "2015-12-06",
      "category": "other"
    },
    {
      "description": "Heart rate",
      "id": "obs_7210bd54-5a32-11f1-afc7-00155dba74fb",
      "encounter": "e221c708-c1e0-47de-9c7a-b949a69ff842",
      "value": "88.0",
      "units": "/min",
      "date": "2015-12-06",
      "category": "other"
    },
    {
      "description": "Respiratory rate",
      "id": "obs_7210bd5e-5a32-11f1-afc7-00155dba74fb",
      "encounter": "e221c708-c1e0-47de-9c7a-b949a69ff842",
      "value": "16.0",
      "units": "/min",
      "date": "2015-12-06",
      "category": "other"
    },
    {
      "description": "Tobacco smoking status NHIS",
      "id": "obs_7210bd7c-5a32-11f1-afc7-00155dba74fb",
      "encounter": "e221c708-c1e0-47de-9c7a-b949a69ff842",
      "value": "Former smoker",
      "units": NaN,
      "date": "2015-12-06",
      "category": "other"
    },
    {
      "description": "Body Height",
      "id": "obs_7210bd90-5a32-11f1-afc7-00155dba74fb",
      "encounter": "d710d8ac-aa5e-43a8-a12c-dc4299764be5",
      "value": "171.6",
      "units": "cm",
      "date": "2016-12-11",
      "category": "body_measurement"
    },
    {
      "description": "Pain severity - 0-10 verbal numeric rating [Score] - Reported",
      "id": "obs_7210bd9a-5a32-11f1-afc7-00155dba74fb",
      "encounter": "d710d8ac-aa5e-43a8-a12c-dc4299764be5",
      "value": "3.0",
      "units": "{score}",
      "date": "2016-12-11",
      "category": "other"
    },
    {
      "description": "Body Weight",
      "id": "obs_7210bdb8-5a32-11f1-afc7-00155dba74fb",
      "encounter": "d710d8ac-aa5e-43a8-a12c-dc4299764be5",
      "value": "85.6",
      "units": "kg",
      "date": "2016-12-11",
      "category": "body_measurement"
    },
    {
      "description": "Body Mass Index",
      "id": "obs_7210bdcc-5a32-11f1-afc7-00155dba74fb",
      "encounter": "d710d8ac-aa5e-43a8-a12c-dc4299764be5",
      "value": "29.1",
      "units": "kg/m2",
      "date": "2016-12-11",
      "category": "body_measurement"
    },
    {
      "description": "Diastolic Blood Pressure",
      "id": "obs_7210bde0-5a32-11f1-afc7-00155dba74fb",
      "encounter": "d710d8ac-aa5e-43a8-a12c-dc4299764be5",
      "value": "79.0",
      "units": "mm[Hg]",
      "date": "2016-12-11",
      "category": "other"
    },
    {
      "description": "Systolic Blood Pressure",
      "id": "obs_7210bdf4-5a32-11f1-afc7-00155dba74fb",
      "encounter": "d710d8ac-aa5e-43a8-a12c-dc4299764be5",
      "value": "130.0",
      "units": "mm[Hg]",
      "date": "2016-12-11",
      "category": "other"
    },
    {
      "description": "Heart rate",
      "id": "obs_7210be08-5a32-11f1-afc7-00155dba74fb",
      "encounter": "d710d8ac-aa5e-43a8-a12c-dc4299764be5",
      "value": "71.0",
      "units": "/min",
      "date": "2016-12-11",
      "category": "other"
    },
    {
      "description": "Respiratory rate",
      "id": "obs_7210be12-5a32-11f1-afc7-00155dba74fb",
      "encounter": "d710d8ac-aa5e-43a8-a12c-dc4299764be5",
      "value": "15.0",
      "units": "/min",
      "date": "2016-12-11",
      "category": "other"
    },
    {
      "description": "Leukocytes [#/volume] in Blood by Automated count",
      "id": "obs_7210be26-5a32-11f1-afc7-00155dba74fb",
      "encounter": "d710d8ac-aa5e-43a8-a12c-dc4299764be5",
      "value": "4.3",
      "units": "10*3/uL",
      "date": "2016-12-11",
      "category": "other"
    },
    {
      "description": "Erythrocytes [#/volume] in Blood by Automated count",
      "id": "obs_7210be3a-5a32-11f1-afc7-00155dba74fb",
      "encounter": "d710d8ac-aa5e-43a8-a12c-dc4299764be5",
      "value": "4.2",
      "units": "10*6/uL",
      "date": "2016-12-11",
      "category": "other"
    },
    {
      "description": "Hemoglobin [Mass/volume] in Blood",
      "id": "obs_7210be44-5a32-11f1-afc7-00155dba74fb",
      "encounter": "d710d8ac-aa5e-43a8-a12c-dc4299764be5",
      "value": "16.1",
      "units": "g/dL",
      "date": "2016-12-11",
      "category": "other"
    },
    {
      "description": "Hematocrit [Volume Fraction] of Blood by Automated count",
      "id": "obs_7210be58-5a32-11f1-afc7-00155dba74fb",
      "encounter": "d710d8ac-aa5e-43a8-a12c-dc4299764be5",
      "value": "38.1",
      "units": "%",
      "date": "2016-12-11",
      "category": "other"
    },
    {
      "description": "MCV [Entitic volume] by Automated count",
      "id": "obs_7210be6c-5a32-11f1-afc7-00155dba74fb",
      "encounter": "d710d8ac-aa5e-43a8-a12c-dc4299764be5",
      "value": "85.2",
      "units": "fL",
      "date": "2016-12-11",
      "category": "other"
    },
    {
      "description": "MCH [Entitic mass] by Automated count",
      "id": "obs_7210be80-5a32-11f1-afc7-00155dba74fb",
      "encounter": "d710d8ac-aa5e-43a8-a12c-dc4299764be5",
      "value": "29.9",
      "units": "pg",
      "date": "2016-12-11",
      "category": "other"
    },
    {
      "description": "MCHC [Mass/volume] by Automated count",
      "id": "obs_7210be8a-5a32-11f1-afc7-00155dba74fb",
      "encounter": "d710d8ac-aa5e-43a8-a12c-dc4299764be5",
      "value": "35.6",
      "units": "g/dL",
      "date": "2016-12-11",
      "category": "other"
    },
    {
      "description": "Erythrocyte distribution width [Entitic volume] by Automated count",
      "id": "obs_7210be9e-5a32-11f1-afc7-00155dba74fb",
      "encounter": "d710d8ac-aa5e-43a8-a12c-dc4299764be5",
      "value": "40.3",
      "units": "fL",
      "date": "2016-12-11",
      "category": "other"
    },
    {
      "description": "Platelets [#/volume] in Blood by Automated count",
      "id": "obs_7210beb2-5a32-11f1-afc7-00155dba74fb",
      "encounter": "d710d8ac-aa5e-43a8-a12c-dc4299764be5",
      "value": "162.2",
      "units": "10*3/uL",
      "date": "2016-12-11",
      "category": "other"
    },
    {
      "description": "Platelet distribution width [Entitic volume] in Blood by Automated count",
      "id": "obs_7210bebc-5a32-11f1-afc7-00155dba74fb",
      "encounter": "d710d8ac-aa5e-43a8-a12c-dc4299764be5",
      "value": "305.3",
      "units": "fL",
      "date": "2016-12-11",
      "category": "other"
    },
    {
      "description": "Platelet mean volume [Entitic volume] in Blood by Automated count",
      "id": "obs_7210bed0-5a32-11f1-afc7-00155dba74fb",
      "encounter": "d710d8ac-aa5e-43a8-a12c-dc4299764be5",
      "value": "11.9",
      "units": "fL",
      "date": "2016-12-11",
      "category": "other"
    },
    {
      "description": "Tobacco smoking status NHIS",
      "id": "obs_7210beee-5a32-11f1-afc7-00155dba74fb",
      "encounter": "d710d8ac-aa5e-43a8-a12c-dc4299764be5",
      "value": "Former smoker",
      "units": NaN,
      "date": "2016-12-11",
      "category": "other"
    },
    {
      "description": "Body Height",
      "id": "obs_7210bf02-5a32-11f1-afc7-00155dba74fb",
      "encounter": "67fecb71-e430-4454-965d-ef1b7e70b248",
      "value": "171.6",
      "units": "cm",
      "date": "2017-12-17",
      "category": "body_measurement"
    },
    {
      "description": "Pain severity - 0-10 verbal numeric rating [Score] - Reported",
      "id": "obs_7210bf0c-5a32-11f1-afc7-00155dba74fb",
      "encounter": "67fecb71-e430-4454-965d-ef1b7e70b248",
      "value": "3.0",
      "units": "{score}",
      "date": "2017-12-17",
      "category": "other"
    },
    {
      "description": "Body Weight",
      "id": "obs_7210bf20-5a32-11f1-afc7-00155dba74fb",
      "encounter": "67fecb71-e430-4454-965d-ef1b7e70b248",
      "value": "87.5",
      "units": "kg",
      "date": "2017-12-17",
      "category": "body_measurement"
    },
    {
      "description": "Body Mass Index",
      "id": "obs_7210bf34-5a32-11f1-afc7-00155dba74fb",
      "encounter": "67fecb71-e430-4454-965d-ef1b7e70b248",
      "value": "29.7",
      "units": "kg/m2",
      "date": "2017-12-17",
      "category": "body_measurement"
    },
    {
      "description": "Diastolic Blood Pressure",
      "id": "obs_7210bf48-5a32-11f1-afc7-00155dba74fb",
      "encounter": "67fecb71-e430-4454-965d-ef1b7e70b248",
      "value": "81.0",
      "units": "mm[Hg]",
      "date": "2017-12-17",
      "category": "other"
    },
    {
      "description": "Systolic Blood Pressure",
      "id": "obs_7210bf5c-5a32-11f1-afc7-00155dba74fb",
      "encounter": "67fecb71-e430-4454-965d-ef1b7e70b248",
      "value": "118.0",
      "units": "mm[Hg]",
      "date": "2017-12-17",
      "category": "other"
    },
    {
      "description": "Heart rate",
      "id": "obs_7210bf66-5a32-11f1-afc7-00155dba74fb",
      "encounter": "67fecb71-e430-4454-965d-ef1b7e70b248",
      "value": "84.0",
      "units": "/min",
      "date": "2017-12-17",
      "category": "other"
    },
    {
      "description": "Respiratory rate",
      "id": "obs_7210bf7a-5a32-11f1-afc7-00155dba74fb",
      "encounter": "67fecb71-e430-4454-965d-ef1b7e70b248",
      "value": "16.0",
      "units": "/min",
      "date": "2017-12-17",
      "category": "other"
    },
    {
      "description": "Total Cholesterol",
      "id": "obs_7210bf8e-5a32-11f1-afc7-00155dba74fb",
      "encounter": "67fecb71-e430-4454-965d-ef1b7e70b248",
      "value": "184.4",
      "units": "mg/dL",
      "date": "2017-12-17",
      "category": "other"
    },
    {
      "description": "Triglycerides",
      "id": "obs_7210bf98-5a32-11f1-afc7-00155dba74fb",
      "encounter": "67fecb71-e430-4454-965d-ef1b7e70b248",
      "value": "113.6",
      "units": "mg/dL",
      "date": "2017-12-17",
      "category": "other"
    },
    {
      "description": "Low Density Lipoprotein Cholesterol",
      "id": "obs_7210bfac-5a32-11f1-afc7-00155dba74fb",
      "encounter": "67fecb71-e430-4454-965d-ef1b7e70b248",
      "value": "85.7",
      "units": "mg/dL",
      "date": "2017-12-17",
      "category": "other"
    },
    {
      "description": "High Density Lipoprotein Cholesterol",
      "id": "obs_7210bfc0-5a32-11f1-afc7-00155dba74fb",
      "encounter": "67fecb71-e430-4454-965d-ef1b7e70b248",
      "value": "76.0",
      "units": "mg/dL",
      "date": "2017-12-17",
      "category": "other"
    },
    {
      "description": "Tobacco smoking status NHIS",
      "id": "obs_7210bfca-5a32-11f1-afc7-00155dba74fb",
      "encounter": "67fecb71-e430-4454-965d-ef1b7e70b248",
      "value": "Former smoker",
      "units": NaN,
      "date": "2017-12-17",
      "category": "other"
    },
    {
      "description": "Body Height",
      "id": "obs_7210bfde-5a32-11f1-afc7-00155dba74fb",
      "encounter": "5d1d35d0-2432-434b-8613-11e3ff6d968a",
      "value": "171.6",
      "units": "cm",
      "date": "2018-12-23",
      "category": "body_measurement"
    },
    {
      "description": "Pain severity - 0-10 verbal numeric rating [Score] - Reported",
      "id": "obs_7210bff2-5a32-11f1-afc7-00155dba74fb",
      "encounter": "5d1d35d0-2432-434b-8613-11e3ff6d968a",
      "value": "3.0",
      "units": "{score}",
      "date": "2018-12-23",
      "category": "other"
    },
    {
      "description": "Body Weight",
      "id": "obs_7210c006-5a32-11f1-afc7-00155dba74fb",
      "encounter": "5d1d35d0-2432-434b-8613-11e3ff6d968a",
      "value": "89.1",
      "units": "kg",
      "date": "2018-12-23",
      "category": "body_measurement"
    },
    {
      "description": "Body Mass Index",
      "id": "obs_7210c01a-5a32-11f1-afc7-00155dba74fb",
      "encounter": "5d1d35d0-2432-434b-8613-11e3ff6d968a",
      "value": "30.3",
      "units": "kg/m2",
      "date": "2018-12-23",
      "category": "body_measurement"
    },
    {
      "description": "Diastolic Blood Pressure",
      "id": "obs_7210c02e-5a32-11f1-afc7-00155dba74fb",
      "encounter": "5d1d35d0-2432-434b-8613-11e3ff6d968a",
      "value": "79.0",
      "units": "mm[Hg]",
      "date": "2018-12-23",
      "category": "other"
    },
    {
      "description": "Systolic Blood Pressure",
      "id": "obs_7210c042-5a32-11f1-afc7-00155dba74fb",
      "encounter": "5d1d35d0-2432-434b-8613-11e3ff6d968a",
      "value": "129.0",
      "units": "mm[Hg]",
      "date": "2018-12-23",
      "category": "other"
    },
    {
      "description": "Heart rate",
      "id": "obs_7210c056-5a32-11f1-afc7-00155dba74fb",
      "encounter": "5d1d35d0-2432-434b-8613-11e3ff6d968a",
      "value": "84.0",
      "units": "/min",
      "date": "2018-12-23",
      "category": "other"
    },
    {
      "description": "Respiratory rate",
      "id": "obs_7210c060-5a32-11f1-afc7-00155dba74fb",
      "encounter": "5d1d35d0-2432-434b-8613-11e3ff6d968a",
      "value": "14.0",
      "units": "/min",
      "date": "2018-12-23",
      "category": "other"
    },
    {
      "description": "Tobacco smoking status NHIS",
      "id": "obs_7210c074-5a32-11f1-afc7-00155dba74fb",
      "encounter": "5d1d35d0-2432-434b-8613-11e3ff6d968a",
      "value": "Former smoker",
      "units": NaN,
      "date": "2018-12-23",
      "category": "other"
    },
    {
      "description": "Body Height",
      "id": "obs_7210c07e-5a32-11f1-afc7-00155dba74fb",
      "encounter": "a6605445-1c2b-4dcb-bccf-67d214e9ba6e",
      "value": "171.6",
      "units": "cm",
      "date": "2019-12-29",
      "category": "body_measurement"
    },
    {
      "description": "Pain severity - 0-10 verbal numeric rating [Score] - Reported",
      "id": "obs_7210c092-5a32-11f1-afc7-00155dba74fb",
      "encounter": "a6605445-1c2b-4dcb-bccf-67d214e9ba6e",
      "value": "1.0",
      "units": "{score}",
      "date": "2019-12-29",
      "category": "other"
    },
    {
      "description": "Body Weight",
      "id": "obs_7210c0a6-5a32-11f1-afc7-00155dba74fb",
      "encounter": "a6605445-1c2b-4dcb-bccf-67d214e9ba6e",
      "value": "89.1",
      "units": "kg",
      "date": "2019-12-29",
      "category": "body_measurement"
    },
    {
      "description": "Body Mass Index",
      "id": "obs_7210c0ba-5a32-11f1-afc7-00155dba74fb",
      "encounter": "a6605445-1c2b-4dcb-bccf-67d214e9ba6e",
      "value": "30.3",
      "units": "kg/m2",
      "date": "2019-12-29",
      "category": "body_measurement"
    },
    {
      "description": "Diastolic Blood Pressure",
      "id": "obs_7210c0ce-5a32-11f1-afc7-00155dba74fb",
      "encounter": "a6605445-1c2b-4dcb-bccf-67d214e9ba6e",
      "value": "87.0",
      "units": "mm[Hg]",
      "date": "2019-12-29",
      "category": "other"
    },
    {
      "description": "Systolic Blood Pressure",
      "id": "obs_7210c0e2-5a32-11f1-afc7-00155dba74fb",
      "encounter": "a6605445-1c2b-4dcb-bccf-67d214e9ba6e",
      "value": "130.0",
      "units": "mm[Hg]",
      "date": "2019-12-29",
      "category": "other"
    },
    {
      "description": "Heart rate",
      "id": "obs_7210c0f6-5a32-11f1-afc7-00155dba74fb",
      "encounter": "a6605445-1c2b-4dcb-bccf-67d214e9ba6e",
      "value": "95.0",
      "units": "/min",
      "date": "2019-12-29",
      "category": "other"
    },
    {
      "description": "Respiratory rate",
      "id": "obs_7210c100-5a32-11f1-afc7-00155dba74fb",
      "encounter": "a6605445-1c2b-4dcb-bccf-67d214e9ba6e",
      "value": "14.0",
      "units": "/min",
      "date": "2019-12-29",
      "category": "other"
    },
    {
      "description": "Tobacco smoking status NHIS",
      "id": "obs_7210c114-5a32-11f1-afc7-00155dba74fb",
      "encounter": "a6605445-1c2b-4dcb-bccf-67d214e9ba6e",
      "value": "Former smoker",
      "units": NaN,
      "date": "2019-12-29",
      "category": "other"
    },
    {
      "description": "QALY",
      "id": "obs_7210c128-5a32-11f1-afc7-00155dba74fb",
      "encounter": NaN,
      "value": "59.5",
      "units": "a",
      "date": "2010-09-04",
      "category": "other"
    },
    {
      "description": "QALY",
      "id": "obs_7210c13c-5a32-11f1-afc7-00155dba74fb",
      "encounter": NaN,
      "value": "60.5",
      "units": "a",
      "date": "2011-09-04",
      "category": "other"
    },
    {
      "description": "QALY",
      "id": "obs_7210c150-5a32-11f1-afc7-00155dba74fb",
      "encounter": NaN,
      "value": "61.5",
      "units": "a",
      "date": "2012-09-04",
      "category": "other"
    },
    {
      "description": "QALY",
      "id": "obs_7210c15a-5a32-11f1-afc7-00155dba74fb",
      "encounter": NaN,
      "value": "62.5",
      "units": "a",
      "date": "2013-09-04",
      "category": "other"
    },
    {
      "description": "QALY",
      "id": "obs_7210c16e-5a32-11f1-afc7-00155dba74fb",
      "encounter": NaN,
      "value": "63.5",
      "units": "a",
      "date": "2014-09-04",
      "category": "other"
    },
    {
      "description": "QALY",
      "id": "obs_7210c182-5a32-11f1-afc7-00155dba74fb",
      "encounter": NaN,
      "value": "64.4",
      "units": "a",
      "date": "2015-09-04",
      "category": "other"
    },
    {
      "description": "QALY",
      "id": "obs_7210c18c-5a32-11f1-afc7-00155dba74fb",
      "encounter": NaN,
      "value": "65.4",
      "units": "a",
      "date": "2016-09-04",
      "category": "other"
    },
    {
      "description": "QALY",
      "id": "obs_7210c1b4-5a32-11f1-afc7-00155dba74fb",
      "encounter": NaN,
      "value": "66.4",
      "units": "a",
      "date": "2017-09-04",
      "category": "other"
    },
    {
      "description": "QALY",
      "id": "obs_7210c1c8-5a32-11f1-afc7-00155dba74fb",
      "encounter": NaN,
      "value": "67.4",
      "units": "a",
      "date": "2018-09-04",
      "category": "other"
    },
    {
      "description": "QALY",
      "id": "obs_7210c1d2-5a32-11f1-afc7-00155dba74fb",
      "encounter": NaN,
      "value": "68.4",
      "units": "a",
      "date": "2019-09-04",
      "category": "other"
    },
    {
      "description": "DALY",
      "id": "obs_7210c1e6-5a32-11f1-afc7-00155dba74fb",
      "encounter": NaN,
      "value": "0.5",
      "units": "a",
      "date": "2010-09-04",
      "category": "other"
    },
    {
      "description": "DALY",
      "id": "obs_7210c1f0-5a32-11f1-afc7-00155dba74fb",
      "encounter": NaN,
      "value": "0.5",
      "units": "a",
      "date": "2011-09-04",
      "category": "other"
    },
    {
      "description": "DALY",
      "id": "obs_7210c204-5a32-11f1-afc7-00155dba74fb",
      "encounter": NaN,
      "value": "0.5",
      "units": "a",
      "date": "2012-09-04",
      "category": "other"
    },
    {
      "description": "DALY",
      "id": "obs_7210c218-5a32-11f1-afc7-00155dba74fb",
      "encounter": NaN,
      "value": "0.5",
      "units": "a",
      "date": "2013-09-04",
      "category": "other"
    },
    {
      "description": "DALY",
      "id": "obs_7210c222-5a32-11f1-afc7-00155dba74fb",
      "encounter": NaN,
      "value": "0.5",
      "units": "a",
      "date": "2014-09-04",
      "category": "other"
    },
    {
      "description": "DALY",
      "id": "obs_7210c240-5a32-11f1-afc7-00155dba74fb",
      "encounter": NaN,
      "value": "0.6",
      "units": "a",
      "date": "2015-09-04",
      "category": "other"
    },
    {
      "description": "DALY",
      "id": "obs_7210c24a-5a32-11f1-afc7-00155dba74fb",
      "encounter": NaN,
      "value": "0.6",
      "units": "a",
      "date": "2016-09-04",
      "category": "other"
    },
    {
      "description": "DALY",
      "id": "obs_7210c25e-5a32-11f1-afc7-00155dba74fb",
      "encounter": NaN,
      "value": "0.6",
      "units": "a",
      "date": "2017-09-04",
      "category": "other"
    },
    {
      "description": "DALY",
      "id": "obs_7210c272-5a32-11f1-afc7-00155dba74fb",
      "encounter": NaN,
      "value": "0.6",
      "units": "a",
      "date": "2018-09-04",
      "category": "other"
    },
    {
      "description": "DALY",
      "id": "obs_7210c27c-5a32-11f1-afc7-00155dba74fb",
      "encounter": NaN,
      "value": "0.6",
      "units": "a",
      "date": "2019-09-04",
      "category": "other"
    },
    {
      "description": "QOLS",
      "id": "obs_7210c290-5a32-11f1-afc7-00155dba74fb",
      "encounter": NaN,
      "value": "1.0",
      "units": "{score}",
      "date": "2010-09-04",
      "category": "other"
    },
    {
      "description": "QOLS",
      "id": "obs_7210c29a-5a32-11f1-afc7-00155dba74fb",
      "encounter": NaN,
      "value": "1.0",
      "units": "{score}",
      "date": "2011-09-04",
      "category": "other"
    },
    {
      "description": "QOLS",
      "id": "obs_7210c2ae-5a32-11f1-afc7-00155dba74fb",
      "encounter": NaN,
      "value": "1.0",
      "units": "{score}",
      "date": "2012-09-04",
      "category": "other"
    },
    {
      "description": "QOLS",
      "id": "obs_7210c2c2-5a32-11f1-afc7-00155dba74fb",
      "encounter": NaN,
      "value": "1.0",
      "units": "{score}",
      "date": "2013-09-04",
      "category": "other"
    },
    {
      "description": "QOLS",
      "id": "obs_7210c2cc-5a32-11f1-afc7-00155dba74fb",
      "encounter": NaN,
      "value": "1.0",
      "units": "{score}",
      "date": "2014-09-04",
      "category": "other"
    },
    {
      "description": "QOLS",
      "id": "obs_7210c2e0-5a32-11f1-afc7-00155dba74fb",
      "encounter": NaN,
      "value": "1.0",
      "units": "{score}",
      "date": "2015-09-04",
      "category": "other"
    },
    {
      "description": "QOLS",
      "id": "obs_7210c2f4-5a32-11f1-afc7-00155dba74fb",
      "encounter": NaN,
      "value": "1.0",
      "units": "{score}",
      "date": "2016-09-04",
      "category": "other"
    },
    {
      "description": "QOLS",
      "id": "obs_7210c308-5a32-11f1-afc7-00155dba74fb",
      "encounter": NaN,
      "value": "1.0",
      "units": "{score}",
      "date": "2017-09-04",
      "category": "other"
    },
    {
      "description": "QOLS",
      "id": "obs_7210c312-5a32-11f1-afc7-00155dba74fb",
      "encounter": NaN,
      "value": "1.0",
      "units": "{score}",
      "date": "2018-09-04",
      "category": "other"
    },
    {
      "description": "QOLS",
      "id": "obs_7210c326-5a32-11f1-afc7-00155dba74fb",
      "encounter": NaN,
      "value": "1.0",
      "units": "{score}",
      "date": "2019-09-04",
      "category": "other"
    }
  ]
}